objectpath/__init__.py
objectpath/shell.py
objectpath/core/__init__.py
objectpath/core/interpreter.py
objectpath/core/parser.py
objectpath/utils/__init__.py
objectpath/utils/colorify.py
objectpath/utils/debugger.py
objectpath/utils/json_ext.py
objectpath/utils/timeutils.py
objectpath_ng-0.6.3.dist-info/LICENSE
objectpath_ng-0.6.3.dist-info/METADATA
objectpath_ng-0.6.3.dist-info/WHEEL
objectpath_ng-0.6.3.dist-info/entry_points.txt
objectpath_ng-0.6.3.dist-info/top_level.txt
objectpath_ng-0.6.3.dist-info/zip-safe
objectpath_ng-0.6.3.dist-info/RECORD
