Metadata-Version: 2.1
Name: objectpath-ng
Version: 0.6.3
Summary: The agile query language for semi-structured data. #JSON
Home-page: http://objectpath.github.io/ObjectPath
Author: Chris Lapa
Author-email: 36723261+chris-lapa@users.noreply.github.com
License: MIT
Keywords: query,tree,JSON,nested structures
Platform: UNKNOWN
Classifier: Development Status :: 6 - Mature
Classifier: Intended Audience :: Developers
Classifier: Intended Audience :: Science/Research
Classifier: License :: OSI Approved :: MIT License
Classifier: Programming Language :: Python
Classifier: Topic :: Software Development :: Libraries :: Python Modules
